codesnap/snaptrace.cpython-38-x86_64-linux-gnu.so
codesnap/codesnap.py
codesnap/__init__.py
codesnap/htmlconverter.py
codesnap/snaptree.py
codesnap/__main__.py
codesnap/tracer.py
codesnap/html/trace_viewer_full.html
codesnap/html/trace_viewer_embedder.html
codesnap-0.1.0.dist-info/LICENSE
codesnap-0.1.0.dist-info/top_level.txt
codesnap-0.1.0.dist-info/WHEEL
codesnap-0.1.0.dist-info/RECORD
codesnap-0.1.0.dist-info/METADATA
codesnap-0.1.0.dist-info/NOTICE
