Metadata-Version: 2.1
Name: codesnap
Version: 0.1.0
Summary: A debugging and profiling tool that can trace and visualize python code
Home-page: https://github.com/gaogaotiantian/codesnap
Author: Tian Gao
Author-email: gaogaotiantian@hotmail.com
License: UNKNOWN
Platform: UNKNOWN
Classifier: Programming Language :: Python :: 3
Classifier: License :: OSI Approved :: Apache Software License
Classifier: Operating System :: OS Independent
Classifier: Topic :: Software Development :: Quality Assurance
Requires-Python: >=3.5
